{
  "source_paper": "s40262-018-0669-y.pdf",
  "resolutions": [
    {"entity_id": "e1", "label": "Drug", "canonical_name": "alirocumab", "action": "MATCHED", "step": "exact", "matched_node": "alirocumab"},
    {"entity_id": "e2", "label": "Type", "canonical_name": "two_compartment_tmdd_michaelis_menten", "action": "CREATED", "step": "new"},
    {"entity_id": "e3", "label": "Organism", "canonical_name": "human", "action": "MATCHED", "step": "exact", "matched_node": "human"},
    {"entity_id": "e4", "label": "Disease", "canonical_name": "hypercholesterolemia", "action": "MATCHED", "step": "exact", "matched_node": "hypercholesterolemia"},
    {"entity_id": "e5", "label": "Model", "canonical_name": "alirocumab_popPK_tmdd_mm_two_compartment", "action": "CREATED", "step": "new"}
  ],
  "summary": {"matched": 3, "created": 2, "flagged": 0}
}
